odoo_resource_assesor/__init__.py
odoo_resource_assesor/resource_assesor.py
odoo_resource_assesor-0.1.1.dist-info/METADATA
odoo_resource_assesor-0.1.1.dist-info/WHEEL
odoo_resource_assesor-0.1.1.dist-info/entry_points.txt
odoo_resource_assesor-0.1.1.dist-info/top_level.txt
odoo_resource_assesor-0.1.1.dist-info/RECORD
