Metadata-Version: 2.1
Name: odoo-resource-assesor
Version: 0.1.1
Summary: A tool to calculate Odoo configuration based on system resources.
Home-page: https://git.coopdevs.org/coopdevs/sandbox/odoo_resource_assesor
Author: Lai
Author-email: sysadmin@coopdevs.org
License: MIT
Platform: UNKNOWN
Classifier: Programming Language :: Python :: 3
Classifier: Operating System :: OS Independent
Classifier: Intended Audience :: Developers
Classifier: Topic :: Software Development :: Build Tools
Requires-Dist: psutil
